{"slug":"acrylic-roof-coatings","taxonomy":"services","route":"/services/acrylic-roof-coatings","title":"Acrylic Roof Coatings in Laredo, TX | Commercial Roofing Contractors of Laredo","metaDescription":"Acrylic roof coatings for Laredo, TX metal roofs and budget-focused retail buildings, weighed against drainage limits and shorter recoat cycles.","internalLinks":[{"anchor":"What a Roof Inspection Actually Covers on a Laredo Warehouse","slug":"commercial-roof-inspection","taxonomy":"services","href":"/services/commercial-roof-inspection"},{"anchor":"Tracking Down Roof Leaks on Laredo's Flat-Roof Warehouses","slug":"commercial-roof-leak-repair","taxonomy":"services","href":"/services/commercial-roof-leak-repair"},{"anchor":"Tear-Off and Deck Replacement on Laredo's Industrial Roofs","slug":"commercial-roof-tear-off-replacement","taxonomy":"services","href":"/services/commercial-roof-tear-off-replacement"},{"anchor":"Perimeter Details That Decide Whether a Roof Survives a Storm","slug":"edge-metal-coping-gutters","taxonomy":"services","href":"/services/edge-metal-coping-gutters"},{"anchor":"Getting a Damaged Roof Dry Before the Next Storm Hits","slug":"emergency-tarp-dry-in","taxonomy":"services","href":"/services/emergency-tarp-dry-in"},{"anchor":"Roof Repair for Rio Bravo's Small Commercial Buildings","slug":"rio-bravo","taxonomy":"locations","href":"/locations/rio-bravo"},{"anchor":"Office Roofs Near the Bridge Sit Above Paperwork That Can't Get Wet","slug":"office-complex-roofing","taxonomy":"project-types","href":"/project-types/office-complex-roofing"},{"anchor":"Roof Documentation Written to Survive the Claims File Review","slug":"insurance-restoration","taxonomy":"industries","href":"/industries/insurance-restoration"}],"html":"<h1>Acrylic Coatings for Metal and Budget-Conscious Roofs in Laredo</h1>\n<p>Acrylic roof coatings cost less than silicone and work well on the right roof, particularly metal roofs and lower-slope surfaces without a significant ponding water problem, which makes them a common recommendation for smaller retail and commercial buildings across Laredo watching the budget on a recoat project.</p>\n\n<h2>Where Acrylic Performs Well</h2>\n<p>Acrylic coatings adhere well to metal roofing, both standing seam and R-panel systems, and restore reflectivity to a faded or chalking factory finish at a lower material cost than silicone. On the smaller retail strips and flex-space buildings scattered through Laredo's commercial corridors, that cost difference often makes acrylic the more practical choice when the roof does not have a chronic ponding issue.</p>\n<p>Acrylic also bonds well to properly prepared single-ply and modified bitumen substrates, giving those roofs a reflective, UV-resistant surface at a lower price point than a full silicone system, provided the roof drains adequately.</p>\n<p>A lot of the small retail buildings we see along San Bernardo Avenue and the older strip centers near downtown fit this profile well: modest roof size, steady but not heavy foot traffic, and an owner who wants to extend the roof's life a real number of years without financing a full recoat at silicone pricing. On those buildings, acrylic is often the coating that matches both the roof condition and the budget the owner actually has.</p>\n\n<h2>The Ponding Water Limitation</h2>\n<p>Acrylic's main weakness compared to silicone is water resistance in areas of standing water. A roof with any meaningful low spots or drainage issues will stress an acrylic coating faster than it would a silicone one, since acrylic can soften or lose adhesion under prolonged water contact.</p>\n<p>We check drainage and slope carefully before recommending acrylic. On a roof with good positive drainage and no chronic ponding, acrylic performs reliably; on a marginal-slope roof with wet spots after every storm, we steer the conversation toward silicone instead, even at the higher material cost.</p>\n\n<h2>Recoat Cycles and Long-Term Cost</h2>\n<p>Acrylic coatings typically need recoating on a shorter interval than silicone, which factors into the real long-term cost comparison between the two systems. A lower upfront cost with a shorter recoat cycle can end up costing about the same as a silicone system over the roof's full service life, depending on how the building owner values near-term budget versus long-term maintenance planning.</p>\n<p>We lay out both scenarios when a building qualifies for either coating type, rather than defaulting to the cheaper option without explaining the maintenance schedule that comes with it.</p>\n\n<h2>Where We Recommend Acrylic Most Often</h2>\n<p>Metal roofs with faded or chalking finishes and good drainage are the clearest fit. Smaller retail, flex-space, and office buildings on a tighter maintenance budget also do well with acrylic when the roof's slope and drainage support it.</p>\n<p>We are more cautious recommending acrylic on the metro's larger flat warehouse and distribution roofs, where marginal slope and the volume of water a summer storm can dump make ponding a more persistent risk than it is on a smaller, better-drained building.</p>\n<p>Government and school buildings with metal roofing on gymnasiums or annex structures also come up often. Those buildings tend to have a fixed annual maintenance budget rather than a capital improvement fund set aside for roofing, and a properly scoped acrylic recoat fits that kind of planned, recurring maintenance cycle better than a bigger one-time expense would.</p>\n<ul>\n<li>Metal roofs with faded or chalking factory finishes and adequate drainage</li>\n<li>Smaller retail and flex-space buildings on a tighter maintenance budget</li>\n<li>Single-ply and modified bitumen roofs with good positive slope</li>\n<li>Roofs due for routine recoat maintenance on a planned cycle</li>\n<li>Buildings prioritizing lower upfront cost over longer recoat intervals</li>\n</ul>\n\n<h2>Preparation Still Determines the Outcome</h2>\n<p>The same preparation standards that apply to silicone apply to acrylic: pressure washing, seam and flashing repair, and priming where the substrate calls for it. Skipping prep to save cost on an already budget-focused coating job tends to produce the shortest-lived results of any roofing decision we see.</p>\n<p>We test for trapped moisture before applying acrylic just as we would with silicone, since coating over a wet substrate produces the same sealed-in problem regardless of which coating chemistry sits on top.</p>\n<p>Weather timing matters for the application itself, as much as the substrate does. Acrylic needs a dry cure window without rain, and Laredo's summer thunderstorms can build quickly on an afternoon that started clear. We watch the forecast closely and stage a coating project around the driest stretch available rather than starting a section that a surprise storm could wash out before it cures.</p>\n\n<h2>Acrylic Coating Questions From Laredo Owners</h2>\n<h3>Is acrylic a good fit for a warehouse roof?</h3>\n<p>Sometimes, if drainage is solid and ponding is not a chronic issue. On roofs with marginal slope, we typically recommend silicone instead for its better standing-water resistance.</p>\n<h3>How often does an acrylic-coated roof need recoating?</h3>\n<p>Generally more often than a silicone system, which is a factor worth weighing against acrylic's lower upfront material cost.</p>\n<h3>Does acrylic work well on metal roofs?</h3>\n<p>Yes, acrylic adheres well to metal and restores reflectivity to a faded finish at a lower cost than silicone, making it a common choice for standing seam and R-panel roofs.</p>\n<h3>What happens if acrylic is applied over standing water areas?</h3>\n<p>It tends to soften or lose adhesion faster than silicone would in the same conditions, which is why we check drainage carefully before recommending it.</p>\n<h3>Is acrylic cheaper than silicone overall?</h3>\n<p>The material cost is lower, but shorter recoat cycles can close some of that gap over the roof's full service life, so we walk through both scenarios before recommending either.</p>","image":"/images/services/acrylic-roof-coatings-commercial-roofing-contractors-laredo-tx.webp"}